CHANGES.rst
CONTRIBUTORS.rst
LICENSE.rst
MANIFEST.in
README.rst
setup.py
docs/conf.py
docs/index.md
src/affinitic/__init__.py
src/affinitic.smartweb.egg-info/PKG-INFO
src/affinitic.smartweb.egg-info/SOURCES.txt
src/affinitic.smartweb.egg-info/dependency_links.txt
src/affinitic.smartweb.egg-info/entry_points.txt
src/affinitic.smartweb.egg-info/namespace_packages.txt
src/affinitic.smartweb.egg-info/not-zip-safe
src/affinitic.smartweb.egg-info/requires.txt
src/affinitic.smartweb.egg-info/top_level.txt
src/affinitic/smartweb/__init__.py
src/affinitic/smartweb/configure.zcml
src/affinitic/smartweb/interfaces.py
src/affinitic/smartweb/permissions.zcml
src/affinitic/smartweb/setuphandlers.py
src/affinitic/smartweb/testing.py
src/affinitic/smartweb/upgrades.py
src/affinitic/smartweb/upgrades.zcml
src/affinitic/smartweb/utils.py
src/affinitic/smartweb/behavior/configure.zcml
src/affinitic/smartweb/behavior/image_scales.py
src/affinitic/smartweb/browser/__init__.py
src/affinitic/smartweb/browser/configure.zcml
src/affinitic/smartweb/browser/import_document.py
src/affinitic/smartweb/browser/overrides/.gitkeep
src/affinitic/smartweb/browser/portlets/__init__.py
src/affinitic/smartweb/browser/portlets/configure.zcml
src/affinitic/smartweb/browser/portlets/image_portlet.pt
src/affinitic/smartweb/browser/portlets/image_portlet.py
src/affinitic/smartweb/browser/static/.gitkeep
src/affinitic/smartweb/browser/static/package.json
src/affinitic/smartweb/browser/static/pnpm-lock.yaml
src/affinitic/smartweb/browser/static/webpack.prod.js
src/affinitic/smartweb/browser/static/dist/index.9b029128174957df01c4.js
src/affinitic/smartweb/browser/static/dist/index.9b029128174957df01c4.js.map
src/affinitic/smartweb/browser/static/dist/index.css
src/affinitic/smartweb/browser/static/dist/index.css.map
src/affinitic/smartweb/browser/static/src/index.js
src/affinitic/smartweb/browser/static/src/js/views.js
src/affinitic/smartweb/browser/static/src/scss/_collections.scss
src/affinitic/smartweb/browser/static/src/scss/_nav.scss
src/affinitic/smartweb/browser/static/src/scss/_view.scss
src/affinitic/smartweb/browser/static/src/scss/main.scss
src/affinitic/smartweb/browser/static/svg/arrow_left_circle.svg
src/affinitic/smartweb/browser/static/svg/plus_circle.svg
src/affinitic/smartweb/contents/__init__.py
src/affinitic/smartweb/contents/configure.zcml
