Metadata-Version: 2.1
Name: affinitic.smartweb
Version: 1.0.0a16
Summary: An agnostic version of IMIO Smartweb
Home-page: http://git.affinitic.be/affinitic-addons/affinitic.smartweb
Author: Affinitic
Author-email: support@affinitic.be
License: GPL version 2
Project-URL: Source, http://git.affinitic.be/affinitic-addons/affinitic.smartweb
Project-URL: Tracker, http://git.affinitic.be/affinitic-addons/affinitic.smartweb/issues
Keywords: Python Plone CMS
Platform: UNKNOWN
Classifier: Environment :: Web Environment
Classifier: Framework :: Plone
Classifier: Framework :: Plone :: Addon
Classifier: Framework :: Plone :: 6.0
Classifier: Programming Language :: Python
Classifier: Programming Language :: Python :: 3.8
Classifier: Operating System :: OS Independent
Classifier: License :: OSI Approved :: GNU General Public License v2 (GPLv2)
Requires-Python: >=3.8
Provides-Extra: test
